funpay_cfn/__init__.py
funpay_cfn/account.py
funpay_cfn/types.py
funpay_cfn/common/__init__.py
funpay_cfn/common/enums.py
funpay_cfn/common/exceptions.py
funpay_cfn/common/utils.py
funpay_cfn/updater/__init__.py
funpay_cfn/updater/events.py
funpay_cfn/updater/runner.py
funpay_cfn-0.1.6.dist-info/METADATA
funpay_cfn-0.1.6.dist-info/WHEEL
funpay_cfn-0.1.6.dist-info/top_level.txt
funpay_cfn-0.1.6.dist-info/RECORD
